knmi/__init__.py
knmi/knmi.py
knmi/metadata.py
knmi/parsers.py
knmi_py-0.2.0.dist-info/METADATA
knmi_py-0.2.0.dist-info/WHEEL
knmi_py-0.2.0.dist-info/licenses/LICENSE
knmi_py-0.2.0.dist-info/RECORD
