Metadata-Version: 2.4
Name: knmi-py
Version: 0.2.0
Summary: A Python API wrapper for KNMI data.
Project-URL: Homepage, https://github.com/EnergieID/KNMI-py
Project-URL: Repository, https://github.com/EnergieID/KNMI-py
Project-URL: Bug Tracker, https://github.com/EnergieID/KNMI-py/issues
Author-email: Jan <jan@energieid.be>, Oscar <oscar@energieid.be>
License: MIT
License-File: LICENSE
Keywords: api,data,knmi,netherlands,pandas,weather
Classifier: Development Status :: 4 - Beta
Classifier: Intended Audience :: Developers
Classifier: Intended Audience :: Science/Research
Classifier: License :: OSI Approved :: MIT License
Classifier: Natural Language :: Dutch
Classifier: Natural Language :: English
Classifier: Operating System :: OS Independent
Classifier: Programming Language :: Python :: 3
Classifier: Programming Language :: Python :: 3.9
Classifier: Programming Language :: Python :: 3.10
Classifier: Programming Language :: Python :: 3.11
Classifier: Programming Language :: Python :: 3.12
Classifier: Programming Language :: Python :: 3.13
Classifier: Topic :: Scientific/Engineering
Classifier: Topic :: Software Development :: Libraries :: Python Modules
Requires-Python: >=3.9
Requires-Dist: beautifulsoup4>=4.9.0
Requires-Dist: pandas>=1.5.3
Requires-Dist: requests>=2.25.0
